LICENSE
README.md
setup.py
arise_predictions/__init__.py
arise_predictions/_version.py
arise_predictions/main.py
arise_predictions.egg-info/PKG-INFO
arise_predictions.egg-info/SOURCES.txt
arise_predictions.egg-info/dependency_links.txt
arise_predictions.egg-info/requires.txt
arise_predictions.egg-info/top_level.txt
arise_predictions/auto_model/__init__.py
arise_predictions/auto_model/build_models.py
arise_predictions/cmd/__init__.py
arise_predictions/cmd/cmd.py
arise_predictions/job_statistics/__init__.py
arise_predictions/job_statistics/analyze_jobs.py
arise_predictions/metrics/__init__.py
arise_predictions/metrics/metrics.py
arise_predictions/perform_predict/__init__.py
arise_predictions/perform_predict/predict.py
arise_predictions/preprocessing/__init__.py
arise_predictions/preprocessing/custom_job_parser.py
arise_predictions/preprocessing/job_parser.py
arise_predictions/utils/__init__.py
arise_predictions/utils/constants.py
arise_predictions/utils/utils.py
tests/__init__.py
tests/test_analyze.py
tests/test_build_meta_learner.py
tests/test_build_models.py
tests/test_categorical_identification.py
tests/test_job_parser.py
tests/test_predict.py
tests/resources/estimator-nonlinear-XGBoost-Regressor-tokens_per_second.pkl
tests/resources/example-demo-mlcommons-config.yaml
tests/resources/job_spec.yaml
tests/resources/mlcommons_inference_data_execution_history.csv
tests/resources/model-search-config.yaml
tests/utils/logger_redirector.py