Metadata-Version: 2.1
Name: arise-predictions
Version: 1.0.3
Summary: ML-based performance prediction for AI workloads configuration management
License: Apache License 2.0
Platform: UNKNOWN
Requires-Python: >=3.9
License-File: LICENSE
